vaarhaft/__init__.py
vaarhaft/fraudscanner/__init__.py
vaarhaft/fraudscanner/client.py
vaarhaft/fraudscanner/config.py
vaarhaft/fraudscanner/request.py
vaarhaft/fraudscanner/response/__init__.py
vaarhaft/fraudscanner/response/base.py
vaarhaft/fraudscanner/response/enums.py
vaarhaft/fraudscanner/response/models.py
vaarhaft_fraudscanner-0.1.10.dist-info/licenses/LICENSE
vaarhaft_fraudscanner-0.1.10.dist-info/METADATA
vaarhaft_fraudscanner-0.1.10.dist-info/WHEEL
vaarhaft_fraudscanner-0.1.10.dist-info/top_level.txt
vaarhaft_fraudscanner-0.1.10.dist-info/RECORD
