Metadata-Version: 2.4
Name: vaarhaft-fraudscanner
Version: 0.1.10
Summary: Python SDK for the Vaarhaft FraudScanner API
Author-email: VAARHAFT <tech@vaarhaft.com>, Jonas Gasteiger <jonas.gasteiger@vaarhaft.com>, Paul Franken <paul.franken@vaarhaft.com>
License: MIT
Project-URL: VAARHAFT, https://www.vaarhaft.com/
Project-URL: API Documentation, https://docs.vaarhaft.com/
Classifier: Programming Language :: Python :: 3
Classifier: Programming Language :: Python :: 3.9
Classifier: Programming Language :: Python :: 3.10
Classifier: Programming Language :: Python :: 3.11
Classifier: Programming Language :: Python :: 3.12
Classifier: Programming Language :: Python :: 3.13
Classifier: License :: OSI Approved :: MIT License
Classifier: Operating System :: OS Independent
Classifier: Development Status :: 4 - Beta
Classifier: Intended Audience :: Developers
Classifier: Topic :: Software Development :: Libraries :: Python Modules
Requires-Python: >=3.9
License-File: LICENSE
Requires-Dist: aiohttp>=3.11.0
Requires-Dist: aiofiles>=24.1.0
Requires-Dist: pydantic>=2.11.0
Requires-Dist: typing_extensions>=4.13.0
Dynamic: license-file
